mem_llm/__init__.py
mem_llm/api_auth.py
mem_llm/api_server.py
mem_llm/base_llm_client.py
mem_llm/builtin_tools.py
mem_llm/builtin_tools_async.py
mem_llm/cli.py
mem_llm/config.yaml.example
mem_llm/config_from_docs.py
mem_llm/config_manager.py
mem_llm/config_presets.py
mem_llm/conversation_analytics.py
mem_llm/conversation_summarizer.py
mem_llm/data_export_import.py
mem_llm/dynamic_prompt.py
mem_llm/knowledge_loader.py
mem_llm/llm_client.py
mem_llm/llm_client_factory.py
mem_llm/logger.py
mem_llm/mem_agent.py
mem_llm/memory_db.py
mem_llm/memory_manager.py
mem_llm/memory_tools.py
mem_llm/prompt_security.py
mem_llm/response_metrics.py
mem_llm/retry_handler.py
mem_llm/thread_safe_db.py
mem_llm/tool_system.py
mem_llm/tool_workspace.py
mem_llm/vector_store.py
mem_llm/web_launcher.py
mem_llm/analytics/__init__.py
mem_llm/analytics/topic_extractor.py
mem_llm/clients/__init__.py
mem_llm/clients/lmstudio_client.py
mem_llm/clients/ollama_client.py
mem_llm/memory/__init__.py
mem_llm/memory/graph/__init__.py
mem_llm/memory/graph/extractor.py
mem_llm/memory/graph/graph_store.py
mem_llm/memory/hierarchy/__init__.py
mem_llm/memory/hierarchy/categorizer.py
mem_llm/memory/hierarchy/layers.py
mem_llm/memory/hierarchy/manager.py
mem_llm/multi_agent/__init__.py
mem_llm/multi_agent/agent_registry.py
mem_llm/multi_agent/base_agent.py
mem_llm/multi_agent/communication.py
mem_llm/web_ui/README.md
mem_llm/web_ui/__init__.py
mem_llm/web_ui/index.html
mem_llm/web_ui/memory.html
mem_llm/web_ui/metrics.html
mem_llm/workflow/__init__.py
mem_llm/workflow/workflow_engine.py
mem_llm-2.4.2.dist-info/METADATA
mem_llm-2.4.2.dist-info/WHEEL
mem_llm-2.4.2.dist-info/entry_points.txt
mem_llm-2.4.2.dist-info/top_level.txt
mem_llm-2.4.2.dist-info/RECORD
