Metadata-Version: 2.2
Name: mem-llm
Version: 2.4.2
Summary: Privacy-first, memory-enabled AI assistant with workflow engine, knowledge graph, multi-agent systems, multi-backend LLM support (Ollama, LM Studio), vector search, and analytics - 100% local and production-ready
Author-email: Cihat Emre Karataş <karatasqemre@gmail.com>
License: MIT
Project-URL: Homepage, https://github.com/emredeveloper/Mem-LLM
Project-URL: Bug Reports, https://github.com/emredeveloper/Mem-LLM/issues
Project-URL: Source, https://github.com/emredeveloper/Mem-LLM
Keywords: llm,ai,memory,agent,multi-agent,chatbot,ollama,lmstudio,multi-backend,local,privacy,vector-search,chromadb,response-metrics,semantic-search,quality-analytics,embedding,streaming,function-calling,tools,async,validation,workspace,collaboration
Classifier: Development Status :: 5 - Production/Stable
Classifier: Intended Audience :: Developers
Classifier: Topic :: Scientific/Engineering :: Artificial Intelligence
Classifier: Topic :: Software Development :: Libraries :: Python Modules
Classifier: Programming Language :: Python :: 3
Classifier: Programming Language :: Python :: 3.10
Classifier: Programming Language :: Python :: 3.11
Classifier: Programming Language :: Python :: 3.12
Requires-Python: >=3.8
Requires-Dist: requests>=2.31.0
Requires-Dist: pyyaml>=6.0.1
Requires-Dist: click>=8.1.0
Requires-Dist: aiohttp>=3.9.0
Requires-Dist: networkx>=3.0
Provides-Extra: dev
Requires-Dist: pytest>=7.4.0; extra == "dev"
Requires-Dist: pytest-cov>=4.1.0; extra == "dev"
Requires-Dist: black>=23.7.0; extra == "dev"
Provides-Extra: web
Requires-Dist: flask>=3.0.0; extra == "web"
Requires-Dist: flask-cors>=4.0.0; extra == "web"
Provides-Extra: api
Requires-Dist: fastapi>=0.104.0; extra == "api"
Requires-Dist: uvicorn[standard]>=0.24.0; extra == "api"
Requires-Dist: websockets>=12.0; extra == "api"
Provides-Extra: postgresql
Requires-Dist: psycopg2-binary>=2.9.9; extra == "postgresql"
Provides-Extra: mongodb
Requires-Dist: pymongo>=4.6.0; extra == "mongodb"
Provides-Extra: databases
Requires-Dist: psycopg2-binary>=2.9.9; extra == "databases"
Requires-Dist: pymongo>=4.6.0; extra == "databases"
Provides-Extra: all
Requires-Dist: pytest>=7.4.0; extra == "all"
Requires-Dist: pytest-cov>=4.1.0; extra == "all"
Requires-Dist: black>=23.7.0; extra == "all"
Requires-Dist: flask>=3.0.0; extra == "all"
Requires-Dist: flask-cors>=4.0.0; extra == "all"
Requires-Dist: fastapi>=0.104.0; extra == "all"
Requires-Dist: uvicorn[standard]>=0.24.0; extra == "all"
Requires-Dist: websockets>=12.0; extra == "all"
Requires-Dist: psycopg2-binary>=2.9.9; extra == "all"
Requires-Dist: pymongo>=4.6.0; extra == "all"
